{
  "course": "CS231N: Deep Learning for Computer Vision",
  "source": "Stanford CS231N Spring 2025 local curated syllabus",
  "note": "Schema aligned with CS224n syllabus format; lecture_id stays in canonical cs231n-lecture-N form for backward compatibility.",
  "lectures": [
    {
      "lecture_id": "cs231n-lecture-1",
      "lecture_number": 1,
      "lecture_title": "Lecture 1: Introduction",
      "course_phase": "Introduction",
      "core_topics": [
        "Computer vision overview",
        "Course overview",
        "Course logistics"
      ],
      "scope_keywords": [
        "computer vision",
        "course overview",
        "course logistics",
        "introduction"
      ],
      "title": "Lecture 1: Introduction",
      "youtube_title": "Lecture 1: Introduction",
      "topic": "Introduction",
      "speaker": null,
      "year": 2025,
      "type": "lecture",
      "custom_order": 1,
      "assets": {
        "slides": [
          "lecture_1_part_1.pdf",
          "lecture_1_part_2.pdf"
        ],
        "video": "cs231n-2025-lecture01-introduction.mp4",
        "transcript": "cs231n-2025-lecture01-introduction_transcript.txt",
        "toc": "lecture-1.json"
      }
    },
    {
      "lecture_id": "cs231n-lecture-2",
      "lecture_number": 2,
      "lecture_title": "Lecture 2: Image Classification with Linear Classifiers",
      "course_phase": "Deep Learning Basics",
      "core_topics": [
        "The data-driven approach",
        "K-nearest neighbor",
        "Linear classifiers",
        "Softmax loss"
      ],
      "scope_keywords": [
        "image classification",
        "linear classifiers",
        "knn",
        "softmax loss",
        "data-driven approach"
      ],
      "title": "Lecture 2: Image Classification with Linear Classifiers",
      "youtube_title": "Lecture 2: Image Classification with Linear Classifiers",
      "topic": "Image Classification with Linear Classifiers",
      "speaker": null,
      "year": 2025,
      "type": "lecture",
      "custom_order": 2,
      "assets": {
        "slides": "lecture_2.pdf",
        "video": "cs231n-2025-lecture02-image-classification-with-linear-classifiers.mp4",
        "transcript": "cs231n-2025-lecture02-image-classification-with-linear-classifiers_transcript.txt",
        "toc": "lecture-2.json"
      }
    },
    {
      "lecture_id": "cs231n-lecture-3",
      "lecture_number": 3,
      "lecture_title": "Lecture 3: Regularization and Optimization",
      "course_phase": "Deep Learning Basics",
      "core_topics": [
        "Regularization",
        "Stochastic Gradient Descent",
        "Momentum",
        "AdaGrad",
        "Adam",
        "Learning rate schedules"
      ],
      "scope_keywords": [
        "regularization",
        "sgd",
        "momentum",
        "adagrad",
        "adam",
        "learning rate schedules",
        "optimization"
      ],
      "title": "Lecture 3: Regularization and Optimization",
      "youtube_title": "Lecture 3: Regularization and Optimization",
      "topic": "Regularization and Optimization",
      "speaker": null,
      "year": 2025,
      "type": "lecture",
      "custom_order": 3,
      "assets": {
        "slides": "lecture_3.pdf",
        "video": "cs231n-2025-lecture03-regularization-and-optimization.mp4",
        "transcript": "cs231n-2025-lecture03-regularization-and-optimization_transcript.txt",
        "toc": "lecture-3.json"
      }
    },
    {
      "lecture_id": "cs231n-lecture-4",
      "lecture_number": 4,
      "lecture_title": "Lecture 4: Neural Networks and Backpropagation",
      "course_phase": "Deep Learning Basics",
      "core_topics": [
        "Multi-layer Perceptron",
        "Backpropagation",
        "Linear backprop example"
      ],
      "scope_keywords": [
        "neural networks",
        "multi-layer perceptron",
        "backpropagation",
        "backprop",
        "derivatives"
      ],
      "title": "Lecture 4: Neural Networks and Backpropagation",
      "youtube_title": "Lecture 4: Neural Networks and Backpropagation",
      "topic": "Neural Networks and Backpropagation",
      "speaker": null,
      "year": 2025,
      "type": "lecture",
      "custom_order": 4,
      "assets": {
        "slides": "lecture_4.pdf",
        "video": "cs231n-2025-lecture04-neural-networks-and-backpropagation.mp4",
        "transcript": "cs231n-2025-lecture04-neural-networks-and-backpropagation_transcript.txt",
        "toc": "lecture-4.json"
      }
    },
    {
      "lecture_id": "cs231n-lecture-5",
      "lecture_number": 5,
      "lecture_title": "Lecture 5: Image Classification with CNNs",
      "course_phase": "Perceiving and Understanding the Visual World",
      "core_topics": [
        "History",
        "Higher-level representations",
        "Image features",
        "Convolution and pooling"
      ],
      "scope_keywords": [
        "cnn",
        "image classification",
        "convolution",
        "pooling",
        "image features",
        "higher-level representations"
      ],
      "title": "Lecture 5: Image Classification with CNNs",
      "youtube_title": "Lecture 5: Image Classification with CNNs",
      "topic": "Image Classification with CNNs",
      "speaker": null,
      "year": 2025,
      "type": "lecture",
      "custom_order": 5,
      "assets": {
        "slides": "lecture_5.pdf",
        "video": "cs231n-2025-lecture05-image-classification-with-cnns.mp4",
        "transcript": "cs231n-2025-lecture05-image-classification-with-cnns_transcript.txt",
        "toc": "lecture-5.json"
      }
    },
    {
      "lecture_id": "cs231n-lecture-6",
      "lecture_number": 6,
      "lecture_title": "Lecture 6: CNN Architectures",
      "course_phase": "Perceiving and Understanding the Visual World",
      "core_topics": [
        "Batch Normalization",
        "Transfer learning",
        "AlexNet",
        "VGG",
        "ResNet"
      ],
      "scope_keywords": [
        "cnn architectures",
        "batch normalization",
        "transfer learning",
        "alexnet",
        "vgg",
        "resnet"
      ],
      "title": "Lecture 6: CNN Architectures",
      "youtube_title": "Lecture 6: CNN Architectures",
      "topic": "CNN Architectures",
      "speaker": null,
      "year": 2025,
      "type": "lecture",
      "custom_order": 6,
      "assets": {
        "slides": "lecture_6.pdf",
        "video": "cs231n-2025-lecture06-cnn-architectures.mp4",
        "transcript": "cs231n-2025-lecture06-cnn-architectures_transcript.txt",
        "toc": "lecture-6.json"
      }
    },
    {
      "lecture_id": "cs231n-lecture-7",
      "lecture_number": 7,
      "lecture_title": "Lecture 7: Recurrent Neural Networks",
      "course_phase": "Perceiving and Understanding the Visual World",
      "core_topics": [
        "RNN",
        "LSTM",
        "GRU",
        "Language modeling",
        "Image captioning",
        "Sequence-to-sequence"
      ],
      "scope_keywords": [
        "rnn",
        "lstm",
        "gru",
        "language modeling",
        "image captioning",
        "sequence-to-sequence"
      ],
      "title": "Lecture 7: Recurrent Neural Networks",
      "youtube_title": "Lecture 7: Recurrent Neural Networks",
      "topic": "Recurrent Neural Networks",
      "speaker": null,
      "year": 2025,
      "type": "lecture",
      "custom_order": 7,
      "assets": {
        "slides": "lecture_7.pdf",
        "video": "cs231n-2025-lecture07-recurrent-neural-networks.mp4",
        "transcript": "cs231n-2025-lecture07-recurrent-neural-networks_transcript.txt",
        "toc": "lecture-7.json"
      }
    },
    {
      "lecture_id": "cs231n-lecture-8",
      "lecture_number": 8,
      "lecture_title": "Lecture 8: Attention and Transformers",
      "course_phase": "Perceiving and Understanding the Visual World",
      "core_topics": [
        "Self-Attention",
        "Transformers"
      ],
      "scope_keywords": [
        "attention",
        "self-attention",
        "transformers",
        "vit"
      ],
      "title": "Lecture 8: Attention and Transformers",
      "youtube_title": "Lecture 8: Attention and Transformers",
      "topic": "Attention and Transformers",
      "speaker": null,
      "year": 2025,
      "type": "lecture",
      "custom_order": 8,
      "assets": {
        "slides": "lecture_8.pdf",
        "video": "cs231n-2025-lecture08-attention-and-transformers.mp4",
        "transcript": "cs231n-2025-lecture08-attention-and-transformers_transcript.txt",
        "toc": "lecture-8.json"
      }
    },
    {
      "lecture_id": "cs231n-lecture-9",
      "lecture_number": 9,
      "lecture_title": "Lecture 9: Object Detection, Image Segmentation, Visualizing and Understanding",
      "course_phase": "Perceiving and Understanding the Visual World",
      "core_topics": [
        "Single-stage detectors",
        "Two-stage detectors",
        "Semantic segmentation",
        "Instance segmentation",
        "Panoptic segmentation",
        "Feature visualization and inversion",
        "Adversarial examples",
        "DeepDream and style transfer"
      ],
      "scope_keywords": [
        "object detection",
        "image segmentation",
        "rcnn",
        "yolo",
        "detr",
        "feature visualization",
        "adversarial examples",
        "style transfer"
      ],
      "title": "Lecture 9: Object Detection, Image Segmentation, Visualizing and Understanding",
      "youtube_title": "Lecture 9: Object Detection, Image Segmentation, Visualizing and Understanding",
      "topic": "Object Detection, Image Segmentation, Visualizing and Understanding",
      "speaker": null,
      "year": 2025,
      "type": "lecture",
      "custom_order": 9,
      "assets": {
        "slides": "lecture_9.pdf",
        "video": "cs231n-2025-lecture09-object-detection-image-segmentation-visualizing.mp4",
        "transcript": "cs231n-2025-lecture09-object-detection-image-segmentation-visualizing_transcript.txt",
        "toc": "lecture-9.json"
      }
    },
    {
      "lecture_id": "cs231n-lecture-10",
      "lecture_number": 10,
      "lecture_title": "Lecture 10: Video Understanding",
      "course_phase": "Perceiving and Understanding the Visual World",
      "core_topics": [
        "Video classification",
        "3D CNN",
        "Two-stream networks",
        "Multimodal video understanding"
      ],
      "scope_keywords": [
        "video understanding",
        "video classification",
        "3d cnn",
        "two-stream networks",
        "multimodal"
      ],
      "title": "Lecture 10: Video Understanding",
      "youtube_title": "Lecture 10: Video Understanding",
      "topic": "Video Understanding",
      "speaker": null,
      "year": 2025,
      "type": "lecture",
      "custom_order": 10,
      "assets": {
        "slides": "lecture_10.pdf",
        "video": "cs231n-2025-lecture10-video-understanding.mp4",
        "transcript": "cs231n-2025-lecture10-video-understanding_transcript.txt",
        "toc": "lecture-10.json"
      }
    },
    {
      "lecture_id": "cs231n-lecture-11",
      "lecture_number": 11,
      "lecture_title": "Lecture 11: Large Scale Distributed Training",
      "course_phase": "Perceiving and Understanding the Visual World",
      "core_topics": [
        "Large scale distributed training"
      ],
      "scope_keywords": [
        "distributed training",
        "large scale training",
        "scaling"
      ],
      "title": "Lecture 11: Large Scale Distributed Training",
      "youtube_title": "Lecture 11: Large Scale Distributed Training",
      "topic": "Large Scale Distributed Training",
      "speaker": null,
      "year": 2025,
      "type": "lecture",
      "custom_order": 11,
      "assets": {
        "slides": "lecture_11.pdf",
        "video": "cs231n-2025-lecture11-large-scale-distributed-training.mp4",
        "transcript": "cs231n-2025-lecture11-large-scale-distributed-training_transcript.txt",
        "toc": "lecture-11.json"
      }
    },
    {
      "lecture_id": "cs231n-lecture-12",
      "lecture_number": 12,
      "lecture_title": "Lecture 12: Self-supervised Learning",
      "course_phase": "Generative and Interactive Visual Intelligence",
      "core_topics": [
        "Pretext tasks",
        "Contrastive learning",
        "Multisensory supervision"
      ],
      "scope_keywords": [
        "self-supervised learning",
        "pretext tasks",
        "contrastive learning",
        "multisensory supervision",
        "dino"
      ],
      "title": "Lecture 12: Self-supervised Learning",
      "youtube_title": "Lecture 12: Self-supervised Learning",
      "topic": "Self-supervised Learning",
      "speaker": null,
      "year": 2025,
      "type": "lecture",
      "custom_order": 12,
      "assets": {
        "slides": "lecture_12.pdf",
        "video": "cs231n-2025-lecture12-self-supervised-learning.mp4",
        "transcript": "cs231n-2025-lecture12-self-supervised-learning_transcript.txt",
        "toc": "lecture-12.json"
      }
    },
    {
      "lecture_id": "cs231n-lecture-13",
      "lecture_number": 13,
      "lecture_title": "Lecture 13: Generative Models 1",
      "course_phase": "Generative and Interactive Visual Intelligence",
      "core_topics": [
        "Variational Autoencoders",
        "Generative Adversarial Network",
        "Autoregressive Models"
      ],
      "scope_keywords": [
        "generative models",
        "vae",
        "gan",
        "autoregressive models",
        "elbo"
      ],
      "title": "Lecture 13: Generative Models 1",
      "youtube_title": "Lecture 13: Generative Models 1",
      "topic": "Generative Models 1",
      "speaker": null,
      "year": 2025,
      "type": "lecture",
      "custom_order": 13,
      "assets": {
        "slides": "lecture_13.pdf",
        "video": "cs231n-2025-lecture13-generative-models-1.mp4",
        "transcript": "cs231n-2025-lecture13-generative-models-1_transcript.txt",
        "toc": "lecture-13.json"
      }
    },
    {
      "lecture_id": "cs231n-lecture-14",
      "lecture_number": 14,
      "lecture_title": "Lecture 14: Generative Models 2",
      "course_phase": "Generative and Interactive Visual Intelligence",
      "core_topics": [
        "Diffusion models"
      ],
      "scope_keywords": [
        "generative models",
        "diffusion models",
        "diffusion"
      ],
      "title": "Lecture 14: Generative Models 2",
      "youtube_title": "Lecture 14: Generative Models 2",
      "topic": "Generative Models 2",
      "speaker": null,
      "year": 2025,
      "type": "lecture",
      "custom_order": 14,
      "assets": {
        "slides": "lecture_14.pdf",
        "video": "cs231n-2025-lecture14-generative-models-2.mp4",
        "transcript": "cs231n-2025-lecture14-generative-models-2_transcript.txt",
        "toc": "lecture-14.json"
      }
    },
    {
      "lecture_id": "cs231n-lecture-15",
      "lecture_number": 15,
      "lecture_title": "Lecture 15: 3D Vision",
      "course_phase": "Generative and Interactive Visual Intelligence",
      "core_topics": [
        "3D shape representations",
        "Shape reconstruction",
        "Neural implicit representations"
      ],
      "scope_keywords": [
        "3d vision",
        "3d shape representations",
        "shape reconstruction",
        "neural implicit representations"
      ],
      "title": "Lecture 15: 3D Vision",
      "youtube_title": "Lecture 15: 3D Vision",
      "topic": "3D Vision",
      "speaker": null,
      "year": 2025,
      "type": "lecture",
      "custom_order": 15,
      "assets": {
        "slides": "lecture_15.pdf",
        "video": "cs231n-2025-lecture15-3d-vision.mp4",
        "transcript": "cs231n-2025-lecture15-3d-vision_transcript.txt",
        "toc": "lecture-15.json"
      }
    },
    {
      "lecture_id": "cs231n-lecture-16",
      "lecture_number": 16,
      "lecture_title": "Lecture 16: Vision and Language",
      "course_phase": "Generative and Interactive Visual Intelligence",
      "core_topics": [
        "Vision and Language"
      ],
      "scope_keywords": [
        "vision and language",
        "vlm",
        "multimodal"
      ],
      "title": "Lecture 16: Vision and Language",
      "youtube_title": "Lecture 16: Vision and Language",
      "topic": "Vision and Language",
      "speaker": null,
      "year": 2025,
      "type": "lecture",
      "custom_order": 16,
      "assets": {
        "slides": "lecture_16.pdf",
        "video": "cs231n-2025-lecture16-vision-and-language.mp4",
        "transcript": "cs231n-2025-lecture16-vision-and-language_transcript.txt",
        "toc": "lecture-16.json"
      }
    },
    {
      "lecture_id": "cs231n-lecture-17",
      "lecture_number": 17,
      "lecture_title": "Lecture 17: Robot Learning",
      "course_phase": "Generative and Interactive Visual Intelligence",
      "core_topics": [
        "Deep Reinforcement Learning",
        "Model Learning",
        "Robotic Manipulation"
      ],
      "scope_keywords": [
        "robot learning",
        "deep reinforcement learning",
        "model learning",
        "robotic manipulation"
      ],
      "title": "Lecture 17: Robot Learning",
      "youtube_title": "Lecture 17: Robot Learning",
      "topic": "Robot Learning",
      "speaker": null,
      "year": 2025,
      "type": "lecture",
      "custom_order": 17,
      "assets": {
        "slides": "lecture_17.pdf",
        "video": "cs231n-2025-lecture17-robot-learning.mp4",
        "transcript": "cs231n-2025-lecture17-robot-learning_transcript.txt",
        "toc": "lecture-17.json"
      }
    },
    {
      "lecture_id": "cs231n-lecture-18",
      "lecture_number": 18,
      "lecture_title": "Lecture 18: Human-Centered AI",
      "course_phase": "Generative and Interactive Visual Intelligence",
      "core_topics": [
        "Human-Centered AI"
      ],
      "scope_keywords": [
        "human-centered ai",
        "human centered ai"
      ],
      "title": "Lecture 18: Human-Centered AI",
      "youtube_title": "Lecture 18: Human-Centered AI",
      "topic": "Human-Centered AI",
      "speaker": null,
      "year": 2025,
      "type": "lecture",
      "custom_order": 18,
      "assets": {
        "slides": null,
        "video": "cs231n-2025-lecture18-human-centered-ai.mp4",
        "transcript": "cs231n-2025-lecture18-human-centered-ai_transcript.txt",
        "toc": "lecture-18.json"
      }
    }
  ],
  "reference_slides_no_video": []
}
